<pkgref spec="1.12" uuid="1CD173B7-DCEE-4B0D-A39C-D7981B8D0655"><config><identifier>net.sourceforge.motofit.motofit.pkg</identifier><version>1</version><description></description><post-install type="none"/><installFrom relative="true" mod="true">../motofit/Motofit</installFrom><installTo mod="true">/Documents/WaveMetrics/Igor Pro 6 User Files/User Procedures/motofit</installTo><flags><followSymbolicLinks/></flags><packageStore type="internal"></packageStore><mod>scripts.postflight.path</mod><mod>installTo</mod><mod>scripts.postflight.isRelativeType</mod><mod>installTo.isAbsoluteType</mod><mod>parent</mod><mod>version</mod><mod>identifier</mod><mod>relocatable</mod><mod>requireAuthorization</mod><mod>installFrom.path</mod><mod>extraFiles</mod><mod>installTo.path</mod><mod>postInstall</mod></config><scripts><postflight relative="true" mod="true">postflight/motofitpostflight.sh</postflight><scripts-element/></scripts><extra-files/></pkgref>