<pkg-contents spec="1.12"><f n="ZIP.xop" o="anz" g="staff" p="16895" pt="/Users/anz/Documents/Andy/MOTOFIT/XOP Toolkit 6/IgorXOPs6/ZIP/Xcode/build/Release/ZIP.xop" m="false" t="file"><f n="Contents" o="anz" g="staff" p="16895"><f n="Info.plist" o="anz" g="staff" p="33279"/><f n="MacOS" o="anz" g="staff" p="16895"><f n="ZIP" o="anz" g="staff" p="33261"/></f><f n="Resources" o="anz" g="staff" p="16895"><f n="English.lproj" o="anz" g="staff" p="16895"><f n="InfoPlist.strings" o="anz" g="staff" p="33279"/></f><f n="ZIP.rsrc" o="anz" g="staff" p="33279"/></f></f></f></pkg-contents>